method_3mo_ahp/__init__.py
method_3mo_ahp/algorithm/__init__.py
method_3mo_ahp/algorithm/src.py
method_3mo_ahp/util/__init__.py
method_3mo_ahp/util/ahp.py
method_3mo_ahp/util/fuzzy_ahp.py
method_3mo_ahp/util/u_n_iii.py
method_3mo_ahp-1.1.2.dist-info/LICENSE
method_3mo_ahp-1.1.2.dist-info/METADATA
method_3mo_ahp-1.1.2.dist-info/WHEEL
method_3mo_ahp-1.1.2.dist-info/top_level.txt
method_3mo_ahp-1.1.2.dist-info/zip-safe
method_3mo_ahp-1.1.2.dist-info/RECORD
