Metadata-Version: 2.1
Name: method-3mo-ahp
Version: 1.1.2
Summary: A Method to Reduce AHP Inconsistency According a Set of Quality Measures
Home-page: https://github.com/Valdecy/Method_3MOAHP
Author: Valdecy Pereira
Author-email: valdecy.pereira@gmail.com
License: GNU
License-File: LICENSE
Requires-Dist: numpy
Requires-Dist: pandas
Requires-Dist: plotly
Requires-Dist: matplotlib
Requires-Dist: scipy
